htx/__init__.py
htx/ccxt/__init__.py
htx/ccxt/htx.py
htx/ccxt/abstract/htx.py
htx/ccxt/async_support/__init__.py
htx/ccxt/async_support/htx.py
htx/ccxt/async_support/base/__init__.py
htx/ccxt/async_support/base/exchange.py
htx/ccxt/async_support/base/throttler.py
htx/ccxt/async_support/base/ws/__init__.py
htx/ccxt/async_support/base/ws/cache.py
htx/ccxt/async_support/base/ws/client.py
htx/ccxt/async_support/base/ws/functions.py
htx/ccxt/async_support/base/ws/future.py
htx/ccxt/async_support/base/ws/order_book.py
htx/ccxt/async_support/base/ws/order_book_side.py
htx/ccxt/base/__init__.py
htx/ccxt/base/decimal_to_precision.py
htx/ccxt/base/errors.py
htx/ccxt/base/exchange.py
htx/ccxt/base/precise.py
htx/ccxt/base/types.py
htx/ccxt/pro/__init__.py
htx/ccxt/pro/htx.py
htx/ccxt/static_dependencies/README.md
htx/ccxt/static_dependencies/__init__.py
htx/ccxt/static_dependencies/bip/__init__.py
htx/ccxt/static_dependencies/bip/addr/P2PKH_addr.py
htx/ccxt/static_dependencies/bip/addr/__init__.py
htx/ccxt/static_dependencies/bip/addr/addr_dec_utils.py
htx/ccxt/static_dependencies/bip/addr/addr_key_validator.py
htx/ccxt/static_dependencies/bip/addr/iaddr_decoder.py
htx/ccxt/static_dependencies/bip/addr/iaddr_encoder.py
htx/ccxt/static_dependencies/bip/base58/__init__.py
htx/ccxt/static_dependencies/bip/base58/base58.py
htx/ccxt/static_dependencies/bip/base58/base58_ex.py
htx/ccxt/static_dependencies/bip/base58/base58_xmr.py
htx/ccxt/static_dependencies/bip/bech32/__init__.py
htx/ccxt/static_dependencies/bip/bech32/bch_bech32.py
htx/ccxt/static_dependencies/bip/bech32/bech32.py
htx/ccxt/static_dependencies/bip/bech32/bech32_base.py
htx/ccxt/static_dependencies/bip/bech32/bech32_ex.py
htx/ccxt/static_dependencies/bip/bech32/segwit_bech32.py
htx/ccxt/static_dependencies/bip/bip32/__init__.py
htx/ccxt/static_dependencies/bip/bip32/bip32_const.py
htx/ccxt/static_dependencies/bip/bip32/bip32_ex.py
htx/ccxt/static_dependencies/bip/bip32/bip32_key_data.py
htx-0.0.124.dist-info/METADATA
htx-0.0.124.dist-info/WHEEL
htx-0.0.124.dist-info/RECORD
